README.rst
setup.cfg
setup.py
src/oneID_connect.egg-info/PKG-INFO
src/oneID_connect.egg-info/SOURCES.txt
src/oneID_connect.egg-info/dependency_links.txt
src/oneID_connect.egg-info/requires.txt
src/oneID_connect.egg-info/top_level.txt
src/oneid/__about__.py
src/oneid/__init__.py
src/oneid/auth.py
src/oneid/exceptions.py
src/oneid/jose.py
src/oneid/jwes.py
src/oneid/jwts.py
src/oneid/keychain.py
src/oneid/nonces.py
src/oneid/service.py
src/oneid/session.py
src/oneid/symcrypt.py
src/oneid/utils.py
src/oneid/data/oneid_admin.yaml
src/oneid/data/oneid_server.yaml
src/oneid/file_adapter/__init__.py
src/oneid/file_adapter/plain_file_handler.py
src/oneid/file_adapter/s3_handler.py